libRDChEBI/__init__.py
libRDChEBI/depiction.py
libRDChEBI/descriptors.py
libRDChEBI/formats.py
libRDChEBI/modification.py
libRDChEBI/registration.py
libRDChEBI/test/__init__.py
libRDChEBI/test/mols.py
libRDChEBI/test/test_lib.py
librdchebi-0.3.9.dist-info/METADATA
librdchebi-0.3.9.dist-info/WHEEL
librdchebi-0.3.9.dist-info/licenses/LICENSE
librdchebi-0.3.9.dist-info/RECORD
