Metadata-Version: 2.4
Name: libRDChEBI
Version: 0.3.9
Summary: RDKit library to deal with ChEBI's chemistry
Project-URL: Homepage, https://github.com/chembl/libRDChEBI
Author: Eloy Félix
Author-email: Nicolas Bosc <chebi-help@ebi.ac.uk>
License: MIT
License-File: LICENSE
Classifier: Intended Audience :: Developers
Classifier: License :: OSI Approved :: MIT License
Classifier: Programming Language :: Python :: 3.10
Classifier: Programming Language :: Python :: 3.11
Classifier: Programming Language :: Python :: 3.12
Classifier: Programming Language :: Python :: 3.13
Requires-Python: >=3.9
Requires-Dist: chembl-structure-pipeline~=1.2.0
Requires-Dist: epam-indigo==1.26.0
Requires-Dist: rdkit>=2023.09.4
